Lab1/blackbox.v
module blackbox(p, m, b, t);
    output p;
    input  m, b, t;
    wire   w06, w14, w15, w18, w27, w28, w29, w30, w42, w52, w58, w72, w75, w79;
    and a21(p, w14, w42);
    or  o11(w14, w29, w28);
    not n60(w28, w29);
    or  o7(w42, w72, w18);
    and a44(w18, w27, w06);
    not n77(w27, w06);
    or  o40(w29, w75, m, b);
    not n94(w75, t);
    or  o2(w06, w52, w58);
    and a61(w52, w15, w30);
    not n90(w15, b);
    not n17(w30, t);
    and a46(w58, t, m, b);
    or  o85(w72, t, m, w79);
    not n20(w79, b);
endmodule // blackbox

Lab1/blackbox_tb.v
module bb_test;

    reg m_in, b_in, t_in;                           // these are inputs to "circuit under test"
                                              // use "reg" not "wire" so can assign a value
    wire p_out;                       // wires for the outputs of "circuit under test"

    blackbox bb1 (p_out, m_in, b_in, t_in);  // the circuit under test
    
    initial begin                             // initial = run at beginning of simulation
                                              // begin/end = associate block with initial
 
        $dumpfile("bb.vcd");                  // name of dump file to create
        $dumpvars(0,bb_test);                 // record all signals of module "sc_test" and sub-modules
                                              // remember to change "sc_test" to the correct
                                              // module name when writing your own test benches
        
        // test all four input combinations
        // remember that 2 inputs means 2^2 = 4 combinations
        // 3 inputs would mean 2^3 = 8 combinations to test, and so on
        // this is very similar to the input columns of a truth table
        m_in = 0; b_in = 0; t_in = 0; # 10;             // set initial values and wait 10 time units
        m_in = 0; b_in = 0; t_in = 1; # 10;
		m_in = 0; b_in = 1; t_in = 0; # 10;
		m_in = 0; b_in = 1; t_in = 1; # 10;
		m_in = 1; b_in = 0; t_in = 0; # 10;
		m_in = 1; b_in = 0; t_in = 1; # 10;
		m_in = 1; b_in = 1; t_in = 0; # 10;
		m_in = 1; b_in = 1; t_in = 1; # 10;
 
        $finish;                              // end the simulation
    end                      
    
    initial
        $monitor("At time %2t, m_in = %d b_in = %d t_in = %d p_out = %d",
                 $time, m_in, b_in, t_in, p_out);
endmodule // bb_test

Lab1/bb.vcd
$date
	Wed Aug 29 20:23:29 2018
$end
$version
	Icarus Verilog
$end
$timescale
	1s
$end
$scope module bb_test $end
$var wire 1 ! p_out $end
$var reg 1 " b_in $end
$var reg 1 # m_in $end
$var reg 1 $ t_in $end
$scope module bb1 $end
$var wire 1 " b $end
$var wire 1 # m $end
$var wire 1 ! p $end
$var wire 1 $ t $end
$var wire 1 % w06 $end
$var wire 1 & w14 $end
$var wire 1 ' w15 $end
$var wire 1 ( w18 $end
$var wire 1 ) w27 $end
$var wire 1 * w28 $end
$var wire 1 + w29 $end
$var wire 1 , w30 $end
$var wire 1 - w42 $end
$var wire 1 . w52 $end
$var wire 1 / w58 $end
$var wire 1 0 w72 $end
$var wire 1 1 w75 $end
$var wire 1 2 w79 $end
$upscope $end
$upscope $end
$enddefinitions $end
#0
$dumpvars
12
11
10
0/
1.
1-
1,
1+
0*
0)
0(
1'
1&
1%
0$
0#
0"
1!
$end
#10
1!
1)
1*
1&
0%
0+
0.
01
0,
1$
#20
0!
0-
0*
11
1,
00
1+
0'
02
0$
1"
#30
1!
1-
01
0,
10
1$
#40
0)
0(
1%
1.
11
1,
1'
12
0$
0"
1#
#50
1)
0%
0.
01
0,
1$
#60
11
1,
0'
02
0$
1"
#70
0)
0(
1%
01
0,
1/
1$
