Lab1/farmer.v
// Complete the farmer module in this file
// Don't put any code in this file besides the farmer circuit

module farmer(e, f, x, g, b);

    output e;
    input f,x,g,b;
    wire w1,w2,w3,not_f,not_x,not_g,not_b;

    not n1 (not_f, f);
    not n2 (not_x, x);
    not n3 (not_g, g);
    not n4 (not_b, b);

    and a1 (w1, not_f,not_x,g,b);
    and a2 (w2, not_f,x,g,not_b);
    and a3 (w3, not_f,x,g,b);


    or o1 (e, w1,w2,w3);


endmodule // farmer

Lab1/farmer_tb.v
module fm_test;


reg f_in, x_in, g_in, b_in;                           // these are inputs to "circuit under test"
// use "reg" not "wire" so can assign a value
wire e_out;                     // wires for the outputs of "circuit under test"

farmer fm1 (e_out, f_in, x_in, g_in, b_in);  // the circuit under test

initial begin                             // initial = run at beginning of simulation
// begin/end = associate block with initial

$dumpfile("fm.vcd");                  // name of dump file to create
$dumpvars(0,fm_test);                 // record all signals of module "sc_test" and sub-modules
// remember to change "sc_test" to the correct
// module name when writing your own test benches

// test all four input combinations
// remember that 2 inputs means 2^2 = 4 combinations
// 3 inputs would mean 2^3 = 8 combinations to test, and so on
// this is very similar to the input columns of a truth table
f_in = 0; x_in = 0; g_in=0; b_in=0; # 10;             // set initial values and wait 10 time units
f_in = 0; x_in = 0; g_in=0; b_in=1; # 10;             // set initial values and wait 10 time units
f_in = 0; x_in = 0; g_in=1; b_in=0; # 10;             // set initial values and wait 10 time units
f_in = 0; x_in = 0; g_in=1; b_in=1; # 10;             // set initial values and wait 10 time units
f_in = 0; x_in = 1; g_in=0; b_in=0; # 10;             // set initial values and wait 10 time units
f_in = 0; x_in = 1; g_in=0; b_in=1; # 10;             // set initial values and wait 10 time units
f_in = 0; x_in = 1; g_in=1; b_in=0; # 10;             // set initial values and wait 10 time units
f_in = 0; x_in = 1; g_in=1; b_in=1; # 10;             // set initial values and wait 10 time units
f_in = 1; x_in = 0; g_in=0; b_in=0; # 10;             // set initial values and wait 10 time units
f_in = 1; x_in = 0; g_in=0; b_in=1; # 10;             // set initial values and wait 10 time units
f_in = 1; x_in = 0; g_in=1; b_in=0; # 10;             // set initial values and wait 10 time units
f_in = 1; x_in = 0; g_in=1; b_in=1; # 10;             // set initial values and wait 10 time units
f_in = 1; x_in = 1; g_in=0; b_in=0; # 10;             // set initial values and wait 10 time units
f_in = 1; x_in = 1; g_in=0; b_in=1; # 10;             // set initial values and wait 10 time units
f_in = 1; x_in = 1; g_in=1; b_in=0; # 10;             // set initial values and wait 10 time units
f_in = 1; x_in = 1; g_in=1; b_in=1; # 10;             // set initial values and wait 10 time units


$finish;                              // end the simulation
end

initial
$monitor("At time %2t, f_in = %d x_in = %d g_in = %d b_in = %d e_out = %d",
$time, f_in, x_in, g_in, b_in, e_out);



endmodule // farmer_test

Lab1/fm.vcd
$date
	Fri Aug 31 15:40:48 2018
$end
$version
	Icarus Verilog
$end
$timescale
	1s
$end
$scope module fm_test $end
$var wire 1 ! e_out $end
$var reg 1 " b_in $end
$var reg 1 # f_in $end
$var reg 1 $ g_in $end
$var reg 1 % x_in $end
$scope module fm1 $end
$var wire 1 " b $end
$var wire 1 ! e $end
$var wire 1 # f $end
$var wire 1 $ g $end
$var wire 1 & not_b $end
$var wire 1 ' not_f $end
$var wire 1 ( not_g $end
$var wire 1 ) not_x $end
$var wire 1 * w1 $end
$var wire 1 + w2 $end
$var wire 1 , w3 $end
$var wire 1 % x $end
$upscope $end
$upscope $end
$enddefinitions $end
#0
$dumpvars
0,
0+
0*
1)
1(
1'
1&
0%
0$
0#
0"
0!
$end
#10
0&
1"
#20
1&
0(
0"
1$
#30
1!
0&
1*
1"
#40
0!
1&
1(
0*
0)
0"
0$
1%
#50
0&
1"
#60
1!
1+
1&
0(
0"
1$
#70
0+
0&
1,
1"
#80
0!
1&
1(
1)
0,
0'
0"
0$
0%
1#
#90
0&
1"
#100
1&
0(
0"
1$
#110
0&
1"
#120
1&
1(
0)
0"
0$
1%
#130
0&
1"
#140
1&
0(
0"
1$
#150
0&
1"
