Lab4/register.v
// register: A register which may be reset to an arbirary value
//
// q      (output) - Current value of register
// d      (input)  - Next value of register
// clk    (input)  - Clock (positive edge-sensitive)
// enable (input)  - Load new value? (yes = 1, no = 0)
// reset  (input)  - Asynchronous reset    (reset = 1)
//
module register(q, d, clk, enable, reset);

    output [31:0] q;
    input  [31:0] d;
    input  clk, enable, reset;

   //  Your implementation goes here
   reg    [31:0] q;
   always@(reset)
      if(reset == 1'b1)
        q <= 0;

  always@(posedge clk)
      if((reset == 1'b0) && (enable == 1'b1))
          q <= d;


endmodule // register



// dffe: D-type flip-flop with enable
//
// q      (output) - Current value of flip flop
// d      (input)  - Next value of flip flop
// clk    (input)  - Clock (positive edge-sensitive)
// enable (input)  - Load new value? (yes = 1, no = 0)
// reset  (input)  - Asynchronous reset   (reset =  1)
//
module dffe(q, d, clk, enable, reset);
   output q;
   reg    q;
   input  d;
   input  clk, enable, reset;

   always@(reset)
     if (reset == 1'b1)
       q <= 0;

   always@(posedge clk)
     if ((reset == 1'b0) && (enable == 1'b1))
       q <= d;
endmodule // dffe

Lab4/register_tb.v
module test;
    reg       clk = 0, enable = 0, reset = 1;  // start by reseting the register file

    /* Make a regular pulsing clock with a 10 time unit period. */
    always #5 clk = !clk;

    reg [4:0] regnum;
    reg [31:0] d;

    //reg [31:0]  = 0;

    wire [31:0] q;
    initial begin
        $dumpfile("register.vcd");
        $dumpvars(0, test);
        # 10  reset = 0;      // stop reseting the register

        # 10
          // write 88 to the register
          enable = 1;
          regnum = 2;
          d = 88;

        # 10
          // try writing to the register when its disabled
          enable = 0;
	        regnum = 2;
	        d = 89;


        // Add your own testcases here!
        # 10
         enable = 1;
         regnum = 3;
         d = 42;

         # 10
         enable = 1;
         regnum = 2;
         d = 27;

         # 10
         enable = 0;
         regnum = 2;
         d = 39;

         # 10
         reset = 1;


         # 10
         enable =1;
         regnum = 0;
         d= 91;

        # 700 $finish;
    end

    initial begin
    end

    register reg1(q, d, clk, enable, reset);

endmodule // test

Lab4/register.vcd
$date
	Thu Sep 20 23:09:57 2018
$end
$version
	Icarus Verilog
$end
$timescale
	1s
$end
$scope module test $end
$var wire 32 ! q [31:0] $end
$var reg 1 " clk $end
$var reg 32 # d [31:0] $end
$var reg 1 $ enable $end
$var reg 5 % regnum [4:0] $end
$var reg 1 & reset $end
$scope module reg1 $end
$var wire 1 " clk $end
$var wire 32 ' d [31:0] $end
$var wire 1 $ enable $end
$var wire 1 & reset $end
$var reg 32 ( q [31:0] $end
$upscope $end
$upscope $end
$enddefinitions $end
#0
$dumpvars
b0 (
bx '
1&
bx %
0$
bx #
0"
b0 !
$end
#5
1"
#10
0"
0&
#15
1"
#20
0"
b1011000 #
b1011000 '
b10 %
1$
#25
b1011000 !
b1011000 (
1"
#30
0"
b1011001 #
b1011001 '
0$
#35
1"
#40
0"
b101010 #
b101010 '
b11 %
1$
#45
b101010 !
b101010 (
1"
#50
0"
b11011 #
b11011 '
b10 %
#55
b11011 !
b11011 (
1"
#60
0"
b100111 #
b100111 '
0$
#65
1"
#70
b0 !
b0 (
0"
1&
#75
1"
#80
0"
b1011011 #
b1011011 '
b0 %
1$
