Lab5/decoder.v
// mips_decode: a decoder for MIPS arithmetic instructions
//
// alu_op      (output) - control signal to be sent to the ALU
// writeenable (output) - should a new value be captured by the register file
// rd_src      (output) - should the destination register be rd (0) or rt (1)
// alu_src2    (output) - should the 2nd ALU source be a register (0) or an immediate (1)
// except      (output) - set to 1 when the opcode/funct combination is unrecognized
// opcode      (input)  - the opcode field from the instruction
// funct       (input)  - the function field from the instruction

module mips_decode(alu_op, writeenable, rd_src, alu_src2, except, opcode, funct);
    output [2:0] alu_op;
    output       writeenable, rd_src, alu_src2, except;
    input  [5:0] opcode, funct;

    // wire add_ = (opcode == 6'b0) & (funct == 6'h20);
    // wire sub_ = (opcode == 6'b0) & (funct == 6'h22);
    // wire and_ = (opcode == 6'b0) & (funct == 6'h24);
    // wire or_ = (opcode == 6'b0) & (funct == 6'h25);
    // wire nor_ = (opcode == 6'b0) & (funct == 6'h27);
    // wire xor_ = (opcode == 6'b0) & (funct == 6'h26);
    //
    // wire addi_ = (opcode == 6'h08);
    // wire andi_ = (opcode == 6'h0c);
    // wire ori_ = (opcode == 6'h0d);
    // wire xori_ = (opcode == 6'h0e);

    wire add_ = (opcode == `OP_OTHER0) & (funct == `OP0_ADD);
    wire sub_ = (opcode == `OP_OTHER0) & (funct == `OP0_SUB);
    wire and_ = (opcode == `OP_OTHER0) & (funct == `OP0_AND);
    wire or_ =  (opcode == `OP_OTHER0) & (funct == `OP0_OR);
    wire nor_ = (opcode == `OP_OTHER0) & (funct == `OP0_NOR);
    wire xor_ = (opcode == `OP_OTHER0) & (funct == `OP0_XOR);

    wire addi_ = (opcode == `OP_ADDI);
    wire andi_ = (opcode == `OP_ANDI);
    wire ori_ = (opcode == `OP_ORI);
    wire xori_ = (opcode == `OP_XORI);

    assign alu_op[2:0] = {(and_|or_|nor_|xor_|andi_|ori_|xori_), (add_|sub_|nor_|xor_|addi_|xori_), (sub_|or_|xor_|ori_|xori_)};
    assign rd_src = addi_ | andi_ | ori_ | xori_;
    assign alu_src2 = addi_ | andi_ | ori_ | xori_;
    assign writeenable = add_ |and_| sub_ | or_ | nor_ | xor_ | addi_ | andi_ | ori_ | xori_;
    assign except = ~writeenable;


endmodule // mips_decode

Lab5/decoder_tb.v
module decoder_test;
    reg [5:0] opcode, funct;

    initial begin
        $dumpfile("decoder.vcd");
        $dumpvars(0, decoder_test);

             opcode = `OP_OTHER0; funct = `OP0_ADD; // try addition
        # 10 opcode = `OP_OTHER0; funct = `OP0_SUB; // try subtraction
        // add more tests here!
        # 10 opcode = `OP_OTHER0; funct = `OP0_AND;
        # 10 opcode = `OP_OTHER0; funct = `OP0_NOR;
        # 10 opcode = `OP_ADDI;
	      # 10 opcode = `OP_ANDI;
	      # 10 opcode = `OP_ORI;
	      # 10 opcode = `OP_XORI;


        # 10 $finish;
    end

    // use gtkwave to test correctness
    wire [2:0] alu_op;
    wire       writeenable, rd_src, alu_src2, except;
    mips_decode decoder(alu_op, writeenable, rd_src, alu_src2, except,
                        opcode, funct);
endmodule // decoder_test

Lab5/decoder.vcd
$date
	Wed Sep 26 18:01:32 2018
$end
$version
	Icarus Verilog
$end
$timescale
	1s
$end
$scope module decoder_test $end
$var wire 1 ! writeenable $end
$var wire 1 " rd_src $end
$var wire 1 # except $end
$var wire 1 $ alu_src2 $end
$var wire 3 % alu_op [2:0] $end
$var reg 6 & funct [5:0] $end
$var reg 6 ' opcode [5:0] $end
$scope module decoder $end
$var wire 1 ( add_ $end
$var wire 1 $ alu_src2 $end
$var wire 1 ) and_ $end
$var wire 1 # except $end
$var wire 6 * funct [5:0] $end
$var wire 1 + nor_ $end
$var wire 6 , opcode [5:0] $end
$var wire 1 - or_ $end
$var wire 1 " rd_src $end
$var wire 1 . sub_ $end
$var wire 1 ! writeenable $end
$var wire 1 / xor_ $end
$var wire 1 0 xori_ $end
$var wire 1 1 ori_ $end
$var wire 1 2 andi_ $end
$var wire 3 3 alu_op [2:0] $end
$var wire 1 4 addi_ $end
$upscope $end
$upscope $end
$enddefinitions $end
#0
$dumpvars
04
b10 3
02
01
00
0/
0.
0-
b0 ,
0+
b100000 *
0)
1(
b0 '
b100000 &
b10 %
0$
0#
0"
1!
$end
#10
b11 %
b11 3
0(
1.
b100010 &
b100010 *
#20
b100 %
b100 3
0.
1)
b100100 &
b100100 *
#30
b110 %
b110 3
0)
1+
b100111 &
b100111 *
#40
b10 %
b10 3
1$
1"
0+
14
b1000 '
b1000 ,
#50
b100 %
b100 3
04
12
b1100 '
b1100 ,
#60
b101 %
b101 3
02
11
b1101 '
b1101 ,
#70
b111 %
b111 3
01
10
b1110 '
b1110 ,
